setup.py
distributions/Binomialdistribution.py
distributions/Gaussiandistribution.py
distributions/Generaldistribution.py
distributions/__init__.py
probability_calc.egg-info/PKG-INFO
probability_calc.egg-info/SOURCES.txt
probability_calc.egg-info/dependency_links.txt
probability_calc.egg-info/not-zip-safe
probability_calc.egg-info/top_level.txt