Metadata-Version: 1.0
Name: probability-calc
Version: 0.1
Summary: Gaussian distributions
Home-page: UNKNOWN
Author: Sayantan Kumar
Author-email: sayantan.jr15@gmail.com
License: UNKNOWN
Platform: UNKNOWN
